sumMe/__init__.py
sumMe/main.py
summe-0.1.dist-info/METADATA
summe-0.1.dist-info/WHEEL
summe-0.1.dist-info/licenses/LICENSE
summe-0.1.dist-info/RECORD
