Metadata-Version: 2.4
Name: sumMe
Version: 0.1
Summary: asdasdasdasdasd
Project-URL: Homepage, https://youtube.com
Project-URL: Issues, https://youtube.com
Author-email: Denis <Denis@mail.ru>
License-File: LICENSE
Classifier: License :: OSI Approved :: MIT License
Classifier: Operating System :: OS Independent
Classifier: Programming Language :: Python :: 3
Requires-Python: >=3.10.0
